jicaiauto/__init__.py
jicaiauto/__version__.py
jicaiauto/jicaiauto.py
jicaiauto/jicaiautoTimer.py
jicaiauto/config/__init__.py
jicaiauto/config/config.py
jicaiauto/data/GLO_VARS.py
jicaiauto/data/__init__.py
jicaiauto/data/favicon.ico
jicaiauto/data/jicaiauto.db
jicaiauto/test/__init__.py
jicaiauto/test/runTestCase.bat
jicaiauto/test/APITest/__init__.py
jicaiauto/test/APITest/test_Jicai_api.py
jicaiauto/test/AppTest/__init__.py
jicaiauto/test/AppTest/conftest.py
jicaiauto/test/AppTest/test_Manzhai_APP_Case1.py
jicaiauto/test/AppTest/test_Manzhai_APP_Case2.py
jicaiauto/test/WebTest/__init__.py
jicaiauto/test/WebTest/conftest.py
jicaiauto/test/WebTest/test_Jicai_WebUI.py
jicaiauto/testCase_template/__init__.py
jicaiauto/testCase_template/test01.py
jicaiauto/testCase_template/test02.py
jicaiauto/testCase_template/test03.py
jicaiauto/utils/__init__.py
jicaiauto/utils/chinese_chromedriver_installer.py
jicaiauto/utils/jicaiautoEmail.py
jicaiauto/utils/jicaiautoHelp.py
jicaiauto/utils/jicaiautoTimer.py
jicaiauto/utils/jicaiautodb.py
jicaiauto-0.0.2.6.dist-info/LICENSE
jicaiauto-0.0.2.6.dist-info/METADATA
jicaiauto-0.0.2.6.dist-info/WHEEL
jicaiauto-0.0.2.6.dist-info/entry_points.txt
jicaiauto-0.0.2.6.dist-info/top_level.txt
jicaiauto-0.0.2.6.dist-info/RECORD
