Metadata-Version: 2.1
Name: jicaiauto
Version: 0.0.2.6
Summary: jicaiauto是对自动化框架的第三次更新，功能覆盖UI自动化与API自动化意在帮助对自动化有更多需求且过多时间写代码的人群，让大家的时间花在业务的实现上
Home-page: https://github.com/jicaiyunshang/jicaiauto
Author: Tser
Author-email: 807447312@qq.com
License: UNKNOWN
Keywords: jicai auto jicaiauto automation test framework
Platform: UNKNOWN
Classifier: Programming Language :: Python :: 3
Classifier: Programming Language :: Python :: 3.6
Classifier: Programming Language :: Python :: 3.7
Classifier: Programming Language :: Python :: 3.8
Classifier: License :: OSI Approved :: Apache Software License
Classifier: Operating System :: OS Independent
Requires-Python: >=3.6
Requires-Dist: pytest
Requires-Dist: pytest-html
Requires-Dist: pytest-ordering
Requires-Dist: selenium
Requires-Dist: jmespath
Requires-Dist: requests
Requires-Dist: pyyaml
Requires-Dist: Appium-Python-Client
